autoupdater/__init__.py
autoupdater/__main__.py
autoupdater/core.py
autoupdater/requirements.py
autoupdater-0.24.0.dist-info/LICENSE
autoupdater-0.24.0.dist-info/METADATA
autoupdater-0.24.0.dist-info/WHEEL
autoupdater-0.24.0.dist-info/RECORD
